varroaclient/__init__.py
varroaclient/client.py
varroaclient/osc/__init__.py
varroaclient/osc/plugin.py
varroaclient/osc/v1/__init__.py
varroaclient/osc/v1/ip_usage.py
varroaclient/osc/v1/security_risk_types.py
varroaclient/osc/v1/security_risks.py
varroaclient/tests/__init__.py
varroaclient/tests/unit/__init__.py
varroaclient/tests/unit/test_client.py
varroaclient/tests/unit/osc/__init__.py
varroaclient/tests/unit/osc/base.py
varroaclient/tests/unit/osc/test_plugin.py
varroaclient/tests/unit/osc/v1/__init__.py
varroaclient/tests/unit/osc/v1/test_ip_usage.py
varroaclient/tests/unit/osc/v1/test_security_risk_types.py
varroaclient/tests/unit/osc/v1/test_security_risks.py
varroaclient/tests/unit/v1/__init__.py
varroaclient/tests/unit/v1/fakes.py
varroaclient/tests/unit/v1/test_ip_usage.py
varroaclient/tests/unit/v1/test_security_risk_types.py
varroaclient/tests/unit/v1/test_security_risks.py
varroaclient/v1/__init__.py
varroaclient/v1/client.py
varroaclient/v1/ip_usage.py
varroaclient/v1/security_risk_types.py
varroaclient/v1/security_risks.py
varroaclient-1.2.1.dist-info/LICENSE
varroaclient-1.2.1.dist-info/METADATA
varroaclient-1.2.1.dist-info/WHEEL
varroaclient-1.2.1.dist-info/entry_points.txt
varroaclient-1.2.1.dist-info/pbr.json
varroaclient-1.2.1.dist-info/top_level.txt
varroaclient-1.2.1.dist-info/RECORD
