Metadata-Version: 2.2
Name: varroaclient
Version: 1.2.1
Summary: Vulnerability management for Opentack - Client
Home-page: https://github.com/NeCTAR-RC/python-varroaclient
Author: ARDC Nectar Cloud Services
Author-email: coreservices@ardc.edu.au
License: Apache-2.0
Keywords: varroa
Classifier: Environment :: OpenStack
Classifier: Intended Audience :: Information Technology
Classifier: Intended Audience :: System Administrators
Classifier: License :: OSI Approved :: Apache Software License
Classifier: Operating System :: POSIX :: Linux
Classifier: Programming Language :: Python
Classifier: Programming Language :: Python :: 3 :: Only
Classifier: Programming Language :: Python :: 3
Classifier: Programming Language :: Python :: 3.10
Classifier: Programming Language :: Python :: 3.12
License-File: LICENSE
Requires-Dist: pbr
Requires-Dist: oslo.utils
Requires-Dist: keystoneauth1
Requires-Dist: osc-lib
Requires-Dist: nectarclient-lib<2.0.0,>=1.0.0
Requires-Dist: python-openstackclient
Dynamic: author
Dynamic: author-email
Dynamic: classifier
Dynamic: description
Dynamic: description-content-type
Dynamic: home-page
Dynamic: keywords
Dynamic: license
Dynamic: requires-dist
Dynamic: summary
